toda/__init__.py
toda/__main__.py
toda/controller.py
toda/model.py
toda/nop.py
toda-0.0.1.dist-info/METADATA
toda-0.0.1.dist-info/WHEEL
toda-0.0.1.dist-info/entry_points.txt
toda-0.0.1.dist-info/top_level.txt
toda-0.0.1.dist-info/RECORD
